app/__init__.py
app/api/__init__.py
app/api/main.py
app/api/routes/__init__.py
app/api/routes/cryptoSystem/__init__.py
app/api/routes/cryptoSystem/asymmetric/__init__.py
app/api/routes/cryptoSystem/asymmetric/ecc.py
app/api/routes/cryptoSystem/asymmetric/elgamal.py
app/api/routes/cryptoSystem/asymmetric/main.py
app/api/routes/cryptoSystem/asymmetric/rsa.py
app/api/routes/cryptoSystem/main.py
app/api/routes/cryptoSystem/symmetric/__init__.py
app/api/routes/cryptoSystem/symmetric/affine.py
app/api/routes/cryptoSystem/symmetric/main.py
app/api/routes/cryptoSystem/symmetric/shift.py
app/api/routes/cryptoSystem/symmetric/vigenere.py
app/api/routes/ellipticeCurve/domain.py
app/api/routes/ellipticeCurve/main.py
app/api/routes/prime/__init__.py
app/api/routes/prime/generator.py
app/api/routes/prime/main.py
app/api/routes/prime/primality.py
app/api/routes/signatureScheme/__init__.py
app/api/routes/signatureScheme/ecdsa.py
app/api/routes/signatureScheme/elgamal.py
app/api/routes/signatureScheme/main.py
app/api/routes/signatureScheme/rsa.py
app/core/__init__.py
app/core/cryptoSystem/asymmetric/__init__.py
app/core/cryptoSystem/asymmetric/ecc.py
app/core/cryptoSystem/asymmetric/elgamal.py
app/core/cryptoSystem/asymmetric/rsa.py
app/core/cryptoSystem/symmetric/affine.py
app/core/cryptoSystem/symmetric/shiftcipher.py
app/core/cryptoSystem/symmetric/vigenere.py
app/core/ellipticCurve/Koblitz.py
app/core/ellipticCurve/__init__.py
app/core/ellipticCurve/curve.py
app/core/ellipticCurve/domain.py
app/core/ellipticCurve/point.py
app/core/hash/md4.py
app/core/hash/sha256.py
app/core/prime/aks.py
app/core/prime/generator.py
app/core/prime/millerRabin.py
app/core/prime/primality.py
app/core/prime/smallPrimes.py
app/core/signatureScheme/ecdsa.py
app/core/signatureScheme/elgamal.py
app/core/signatureScheme/rsa.py
app/core/utils.py
app/main.py
app/schemas/__init__.py
app/schemas/ecc.py
app/schemas/ecdsa.py
app/schemas/elgamal.py
app/schemas/rsa.py
app/schemas/signature.py
cryptotool_backend-0.1.0.dist-info/METADATA
cryptotool_backend-0.1.0.dist-info/WHEEL
cryptotool_backend-0.1.0.dist-info/RECORD
